cook/__init__.py
cook/__main__.py
cook/cli.py
cook/configuration.py
cook/dateparser.py
cook/exceptions.py
cook/format.py
cook/http.py
cook/mesos.py
cook/metrics.py
cook/plugins.py
cook/progress.py
cook/querying.py
cook/terminal.py
cook/util.py
cook/version.py
cook/subcommands/__init__.py
cook/subcommands/admin.py
cook/subcommands/cat.py
cook/subcommands/config.py
cook/subcommands/jobs.py
cook/subcommands/kill.py
cook/subcommands/ls.py
cook/subcommands/show.py
cook/subcommands/ssh.py
cook/subcommands/submit.py
cook/subcommands/tail.py
cook/subcommands/usage.py
cook/subcommands/wait.py
cook_client-3.9.5.dist-info/METADATA
cook_client-3.9.5.dist-info/WHEEL
cook_client-3.9.5.dist-info/entry_points.txt
cook_client-3.9.5.dist-info/top_level.txt
cook_client-3.9.5.dist-info/RECORD
