Metadata-Version: 2.1
Name: cook-client
Version: 3.9.5
Summary: Two Sigma's Cook CLI
Home-page: UNKNOWN
License: UNKNOWN
Platform: UNKNOWN
Requires-Dist: arrow
Requires-Dist: blessed
Requires-Dist: humanfriendly
Requires-Dist: python-dateutil (>=2.8.1)
Requires-Dist: pytz
Requires-Dist: requests
Requires-Dist: tabulate
Requires-Dist: tenacity
Requires-Dist: tzlocal
